khmer_latin_name_transformer/__init__.py
khmer_latin_name_transformer/km_latin_names.fst
khmer_latin_name_transformer/km_pronounce.fst
khmer_latin_name_transformer/latin_km_names.fst
khmer_latin_name_transformer-0.0.4.dist-info/LICENSE
khmer_latin_name_transformer-0.0.4.dist-info/METADATA
khmer_latin_name_transformer-0.0.4.dist-info/WHEEL
khmer_latin_name_transformer-0.0.4.dist-info/top_level.txt
khmer_latin_name_transformer-0.0.4.dist-info/RECORD
