Metadata-Version: 2.1
Name: khmer_latin_name_transformer
Version: 0.0.4
Summary: Transform Khmer Personal Name into Latin and vice-versa.
Home-page: https://github.com/seanghay/khmer-latin-name-transformer
Author: Seanghay Yath
Author-email: seanghay.dev@gmail.com
License: Apache License 2.0
Classifier: Programming Language :: Python :: 3
Classifier: Operating System :: OS Independent
Classifier: Intended Audience :: Developers
Classifier: Natural Language :: English
Requires-Python: >3.5
License-File: LICENSE
Requires-Dist: pynini
